odoo/addons/shopinvader_product_stock/README.rst
odoo/addons/shopinvader_product_stock/__init__.py
odoo/addons/shopinvader_product_stock/__manifest__.py
odoo/addons/shopinvader_product_stock/data/ir_export_product.xml
odoo/addons/shopinvader_product_stock/data/queue_job_channel_data.xml
odoo/addons/shopinvader_product_stock/data/queue_job_function_data.xml
odoo/addons/shopinvader_product_stock/i18n/shopinvader_product_stock.pot
odoo/addons/shopinvader_product_stock/models/__init__.py
odoo/addons/shopinvader_product_stock/models/product_product.py
odoo/addons/shopinvader_product_stock/models/shopinvader_backend.py
odoo/addons/shopinvader_product_stock/models/shopinvader_variant.py
odoo/addons/shopinvader_product_stock/models/stock_move.py
odoo/addons/shopinvader_product_stock/readme/CONTRIBUTORS.rst
odoo/addons/shopinvader_product_stock/readme/CREDITS.rst
odoo/addons/shopinvader_product_stock/readme/DESCRIPTION.rst
odoo/addons/shopinvader_product_stock/readme/HISTORY.rst
odoo/addons/shopinvader_product_stock/static/description/index.html
odoo/addons/shopinvader_product_stock/tests/__init__.py
odoo/addons/shopinvader_product_stock/tests/common.py
odoo/addons/shopinvader_product_stock/tests/test_product.py
odoo/addons/shopinvader_product_stock/tests/test_stock_move.py
odoo/addons/shopinvader_product_stock/views/shopinvader_backend.xml
odoo13_addon_shopinvader_product_stock-13.0.3.0.1.dist-info/METADATA
odoo13_addon_shopinvader_product_stock-13.0.3.0.1.dist-info/WHEEL
odoo13_addon_shopinvader_product_stock-13.0.3.0.1.dist-info/top_level.txt
odoo13_addon_shopinvader_product_stock-13.0.3.0.1.dist-info/RECORD
