Metadata-Version: 2.1
Name: odoo13-addon-shopinvader-product-stock
Version: 13.0.3.0.1
Summary: This module is used to choose a stock field during theexport (by backend)
Home-page: https://github.com/shopinvader/odoo-shopinvader
Author: Akretion,ACSONE SA/NV,Camptocamp
License: AGPL-3
Platform: UNKNOWN
Classifier: Programming Language :: Python
Classifier: Framework :: Odoo
Classifier: Framework :: Odoo :: 13.0
Classifier: License :: OSI Approved :: GNU Affero General Public License v3
Classifier: Development Status :: 5 - Production/Stable
Requires-Python: >=3.5
Requires-Dist: odoo13-addon-connector-search-engine
Requires-Dist: odoo13-addon-queue-job
Requires-Dist: odoo13-addon-shopinvader
Requires-Dist: odoo13-addon-shopinvader-search-engine
Requires-Dist: odoo (<13.1dev,>=13.0a)
Requires-Dist: slugify
